fastapi_websocket_stabilizer/__init__.py
fastapi_websocket_stabilizer/_models.py
fastapi_websocket_stabilizer/config.py
fastapi_websocket_stabilizer/exceptions.py
fastapi_websocket_stabilizer/logging_utils.py
fastapi_websocket_stabilizer/manager.py
fastapi_websocket_stabilizer-1.1.0.dist-info/licenses/LICENSE
fastapi_websocket_stabilizer-1.1.0.dist-info/METADATA
fastapi_websocket_stabilizer-1.1.0.dist-info/WHEEL
fastapi_websocket_stabilizer-1.1.0.dist-info/top_level.txt
fastapi_websocket_stabilizer-1.1.0.dist-info/RECORD
