Metadata-Version: 2.4
Name: fastapi-websocket-stabilizer
Version: 1.1.0
Summary: A production-ready WebSocket stabilization layer for FastAPI applications
Author: FastAPI WebSocket Stabilizer Contributors
License-Expression: MIT
Project-URL: Homepage, https://github.com/yuuichieguchi/fastapi-websocket-stabilizer
Project-URL: Repository, https://github.com/yuuichieguchi/fastapi-websocket-stabilizer
Project-URL: Documentation, https://github.com/yuuichieguchi/fastapi-websocket-stabilizer#readme
Project-URL: Issues, https://github.com/yuuichieguchi/fastapi-websocket-stabilizer/issues
Keywords: fastapi,websocket,connection-management,heartbeat,graceful-shutdown
Classifier: Development Status :: 4 - Beta
Classifier: Environment :: Web Environment
Classifier: Intended Audience :: Developers
Classifier: Operating System :: OS Independent
Classifier: Programming Language :: Python
Classifier: Programming Language :: Python :: 3
Classifier: Programming Language :: Python :: 3.10
Classifier: Programming Language :: Python :: 3.11
Classifier: Programming Language :: Python :: 3.12
Classifier: Topic :: Internet :: WWW/HTTP
Classifier: Topic :: Software Development :: Libraries :: Python Modules
Requires-Python: >=3.10
License-File: LICENSE
Requires-Dist: fastapi>=0.95.0
Provides-Extra: dev
Requires-Dist: pytest>=7.0; extra == "dev"
Requires-Dist: pytest-asyncio>=0.21.0; extra == "dev"
Requires-Dist: pytest-cov>=4.0; extra == "dev"
Requires-Dist: black>=23.0; extra == "dev"
Requires-Dist: ruff>=0.1.0; extra == "dev"
Requires-Dist: mypy>=1.0; extra == "dev"
Requires-Dist: uvicorn>=0.20.0; extra == "dev"
Dynamic: license-file
